quicki18n/__init__.py
quicki18n/i18n.py
quick_i18n-0.1.2.dist-info/LICENSE
quick_i18n-0.1.2.dist-info/METADATA
quick_i18n-0.1.2.dist-info/WHEEL
quick_i18n-0.1.2.dist-info/top_level.txt
quick_i18n-0.1.2.dist-info/RECORD
