Metadata-Version: 2.1
Name: quick-i18n
Version: 0.1.2
Summary: A quick and easy internationalization library for Python.
Home-page: https://github.com/urands/quick-i18n
Author: Iu Bell
Author-email: Iu Bell <uran.ds@gmail.com>
License: MIT License
Project-URL: Homepage, https://github.com/urands/quick-i18n
Project-URL: Documentation, https://github.com/urands/quick-i18n#readme
Project-URL: Source, https://github.com/urands/quick-i18n
Project-URL: Tracker, https://github.com/urands/quick-i18n/issues
Keywords: i18n,internationalization,translation,localization,python
Classifier: Development Status :: 4 - Beta
Classifier: Programming Language :: Python :: 3
Classifier: Programming Language :: Python :: 3.6
Classifier: Programming Language :: Python :: 3.7
Classifier: Programming Language :: Python :: 3.8
Classifier: Programming Language :: Python :: 3.9
Classifier: Programming Language :: Python :: 3.10
Classifier: Operating System :: OS Independent
Classifier: Intended Audience :: Developers
Classifier: Topic :: Software Development :: Internationalization
Classifier: License :: OSI Approved :: MIT License
Requires-Python: >=3.6
License-File: LICENSE
Requires-Dist: python-slugify>=4.0.1
